scenestats/__init__.py
scenestats-0.0.1.dist-info/METADATA
scenestats-0.0.1.dist-info/WHEEL
scenestats-0.0.1.dist-info/top_level.txt
scenestats-0.0.1.dist-info/RECORD
